README
setup.py
src/nous/__init__.py
src/nous.mailpost.egg-info/PKG-INFO
src/nous.mailpost.egg-info/SOURCES.txt
src/nous.mailpost.egg-info/dependency_links.txt
src/nous.mailpost.egg-info/entry_points.txt
src/nous.mailpost.egg-info/requires.txt
src/nous.mailpost.egg-info/top_level.txt
src/nous.mailpost.egg-info/zip-safe
src/nous/mailpost/MailBoxerTools.py
src/nous/mailpost/__init__.py
src/nous/mailpost/mailboxer_tools.py
src/nous/mailpost/smtp2zope.py
src/nous/mailpost/tests/__init__.py
src/nous/mailpost/tests/test_mailpost.py