Metadata-Version: 1.0
Name: nous.mailpost
Version: 0.5.2
Summary: Email processor that posts the email received to a url
Home-page: http://github.com/Ignas/nous.mailpost/
Author: Ignas Mikalajunas
Author-email: ignas@nous.lt
License: GPL
Platform: UNKNOWN
Classifier: Development Status :: 3 - Alpha
Classifier: Environment :: Web Environment
Classifier: Topic :: Communications :: Email
Classifier: Intended Audience :: Developers
Classifier: License :: OSI Approved :: GNU General Public License (GPL)
Classifier: Programming Language :: Python
